<?xml version="1.0" ?>
<!DOCTYPE PISI SYSTEM "https://www.pisilinux.org/projeler/pisi/pisi-spec.dtd">
<PISI>
    <Source>
        <Name>audacity</Name>
        <Homepage>https://www.audacityteam.org/</Homepage>
        <Packager>
            <Name>PisiLinux Community</Name>
            <Email>admins@pisilinux.org</Email>
        </Packager>
        <PartOf>multimedia.sound</PartOf>
        <License>GPLv2</License>
        <IsA>app:gui</IsA>
        <Icon>Audacity</Icon>
        <Summary>Multi-track audio editor and recorder</Summary>
        <Description>With Audacity, you can cut, copy, splice or mix sounds together; change the speed or pitch of a recording and much more. Editing is very fast and provides unlimited undo/redo. There are digital effects and spectrum analysis tools. Supported file formats include Ogg Vorbis, MP3, WAV, AIFF, and AU..</Description>
        <Archive sha1sum="53dedd778c0e5bf5f3d85e34635e9494660ec5e5" type="targz">https://github.com/audacity/audacity/archive/Audacity-3.1.3.tar.gz</Archive>
        <BuildDependencies>
            <Dependency>cmake</Dependency>
            <Dependency>wxGTK3</Dependency>
            <Dependency>lv2-devel</Dependency>
            <Dependency>flac-devel</Dependency>
            <Dependency>gtk3-devel</Dependency>
            <Dependency>lame-devel</Dependency>
            <Dependency>expat-devel</Dependency>
            <Dependency>glib2-devel</Dependency>
            <Dependency>wxGTK-devel</Dependency>
            <Dependency>wxBase-devel</Dependency>
            <Dependency>ffmpeg-devel</Dependency>
            <Dependency>libmad-devel</Dependency>
            <Dependency>libogg-devel</Dependency>
            <Dependency>taglib-devel</Dependency>
            <Dependency>twolame-devel</Dependency>
            <Dependency>alsa-lib-devel</Dependency>
            <Dependency>libid3tag-devel</Dependency>
            <Dependency>libvorbis-devel</Dependency>
            <Dependency>libsndfile-devel</Dependency>
            <Dependency>soundtouch-devel</Dependency>
            <Dependency>gdk-pixbuf-devel</Dependency>
            <Dependency>desktop-file-utils</Dependency>
            <Dependency>libsamplerate-devel</Dependency>
            <Dependency>vamp-plugin-sdk-devel</Dependency>
            <Dependency>jack-audio-connection-kit-devel</Dependency>
        </BuildDependencies>
        <Patches>
            <Patch level="1">342c4b588f2f069a2df2157ac166237a54277b3a.patch</Patch>
            <Patch level="1">efc11c4ac50ac51cd71d4dcfa84e63b11000c3f5.patch</Patch>
        </Patches>
    </Source>

    <Package>
        <Name>audacity</Name>
        <Summary>Multi-track audio editor and recorder</Summary>
        <RuntimeDependencies>
            <Dependency>lv2</Dependency>
            <Dependency>flac</Dependency>
            <Dependency>gtk3</Dependency>
            <Dependency>expat</Dependency>
            <Dependency>glib2</Dependency>
            <Dependency>ffmpeg</Dependency>
            <Dependency>libogg</Dependency>
            <Dependency>libmad</Dependency>
            <Dependency>libgcc</Dependency>
            <Dependency>wxBase</Dependency>
            <Dependency>wxGTK3</Dependency>
            <Dependency>twolame</Dependency>
            <Dependency>alsa-lib</Dependency>
            <Dependency>libid3tag</Dependency>
            <Dependency>libvorbis</Dependency>
            <Dependency>libsndfile</Dependency>
            <Dependency>soundtouch</Dependency>
            <Dependency>gdk-pixbuf</Dependency>
            <Dependency>soundtouch</Dependency>
            <Dependency>wxGTK-common</Dependency>
            <Dependency>libsamplerate</Dependency>
            <Dependency>vamp-plugin-sdk</Dependency>
            <Dependency>jack-audio-connection-kit</Dependency>
            <!-- Only needed for runtime -->
            <Dependency>lame</Dependency>
        </RuntimeDependencies>
        <Files>
            <Path fileType="man">/usr/share/man</Path>
            <Path fileType="executable">/usr/bin</Path>
            <Path fileType="data">/usr/share/mime</Path>
            <Path fileType="data">/usr/share/icons</Path>
            <Path fileType="data">/usr/share/pixmaps</Path>
            <Path fileType="data">/usr/share/appdata</Path>
            <Path fileType="data">/usr/share/audacity</Path>
            <Path fileType="doc">/usr/share/doc/audacity</Path>
            <Path fileType="localedata">/usr/share/locale</Path>
            <Path fileType="data">/usr/share/applications</Path>
        </Files>
   </Package>

    <History>
        <Update release="7">
            <Date>2022-07-28</Date>
            <Version>3.1.3</Version>
            <Comment>Version bump</Comment>
            <Name>Mustafa Cinasal</Name>
            <Email>muscnsl@gmail.com</Email>
        </Update>
        <Update release="6">
            <Date>2020-05-21</Date>
            <Version>2.4.1</Version>
            <Comment>Rebuild.</Comment>
            <Name>Mustafa Cinasal</Name>
            <Email>muscnsl@pisilinux.org</Email>
        </Update>
        <Update release="6">
            <Date>2020-05-21</Date>
            <Version>2.4.1</Version>
            <Comment>Patch version bump.</Comment>
            <Name>Blue Devil</Name>
            <Email>bluedevil@sctzine.com</Email>
        </Update>
        <Update release="5">
            <Date>2020-05-21</Date>
            <Version>2.4.0</Version>
            <Comment>Minor version bump.</Comment>
            <Name>Blue Devil</Name>
            <Email>bluedevil@sctzine.com</Email>
        </Update>
        <Update release="4">
            <Date>2020-01-30</Date>
            <Version>2.3.3</Version>
            <Comment>Version bump.</Comment>
            <Name>Mustafa Cinasal</Name>
            <Email>muscnsl@pisilinux.org</Email>
        </Update>
        <Update release="3">
            <Date>2019-03-13</Date>
            <Version>2.3.1</Version>
            <Comment>Version bump.</Comment>
            <Name>Mustafa Cinasal</Name>
            <Email>muscnsl@pisilinux.org</Email>
        </Update>
        <Update release="2">
            <Date>2018-04-28</Date>
            <Version>2.2.2</Version>
            <Comment>Rebuild ffmpeg.</Comment>
            <Name>Mustafa Cinasal</Name>
            <Email>muscnsl@pisilinux.org</Email>
        </Update>
        <Update release="1">
            <Date>2018-04-04</Date>
            <Version>2.2.2</Version>
            <Comment>First release for Pisi Linux 2.0.</Comment>
            <Name>Stefan Gronewold</Name>
            <Email>groni@pisilinux.org</Email>
        </Update>
    </History>
</PISI>
