<?xml version="1.0" ?>
<!DOCTYPE PISI SYSTEM "http://www.pisilinux.org/projeler/pisi/pisi-spec.dtd">
<PISI>
    <Source>
        <Name>goffice</Name>
        <Homepage>https://git.gnome.org/browse/goffice</Homepage>
        <Packager>
            <Name>PisiLinux Community</Name>
            <Email>admins@pisilinux.org</Email>
        </Packager>
        <License>GPLv3</License>
        <IsA>library</IsA>
        <Summary>A GLib/GTK+ set of document-centric objects and charting library</Summary>
        <Description>A GLib/GTK+ set of document-centric objects and charting library</Description>
        <Archive sha1sum="dd770671d59b1ed6861db8797a70f4f5869a8277" type="tarxz">http://ftp.gnome.org/pub/gnome/sources/goffice/0.10/goffice-0.10.51.tar.xz</Archive>
        <BuildDependencies>
            <Dependency>intltool</Dependency>
            <Dependency>gtk-doc</Dependency>
            <Dependency>atk-devel</Dependency>
            <Dependency>gtk3-devel</Dependency>
            <Dependency>python-six</Dependency>
            <Dependency>cairo-devel</Dependency>
            <Dependency>glib2-devel</Dependency>
            <Dependency>pango-devel</Dependency>
            <Dependency>libgsf-devel</Dependency>
            <Dependency>librsvg-devel</Dependency>
            <Dependency>libxml2-devel</Dependency>
            <Dependency>libxslt-devel</Dependency>
            <Dependency>gdk-pixbuf-devel</Dependency>
            <Dependency>libspectre-devel</Dependency>
            <Dependency>gobject-introspection-devel</Dependency>
        </BuildDependencies>
    </Source>

    <Package>
        <Name>goffice</Name>
        <RuntimeDependencies>
            <Dependency>atk</Dependency>
            <Dependency>gtk3</Dependency>
            <Dependency>cairo</Dependency>
            <Dependency>glib2</Dependency>
            <Dependency>pango</Dependency>
            <Dependency>libgsf</Dependency>
            <Dependency>librsvg</Dependency>
            <Dependency>libxml2</Dependency>
            <Dependency>libxslt</Dependency>
            <Dependency>harfbuzz</Dependency>
            <Dependency>gdk-pixbuf</Dependency>
            <Dependency>libspectre</Dependency>
        </RuntimeDependencies>
        <Files>
            <Path fileType="library">/usr/lib</Path>
            <Path fileType="data">/usr/share</Path>
            <Path fileType="data">/usr/share/goffice</Path>
            <Path fileType="localedata">/usr/share/locale</Path>
            <Path fileType="doc">/usr/share/doc</Path>
        </Files>
    </Package>
    
    <Package>
        <Name>goffice-devel</Name>
        <Summary>Development files for goffice</Summary>
        <RuntimeDependencies>
            <Dependency release="current">goffice</Dependency>
            <Dependency>gtk3-devel</Dependency>
            <Dependency>cairo-devel</Dependency>
            <Dependency>glib2-devel</Dependency>
            <Dependency>pango-devel</Dependency>
            <Dependency>libgsf-devel</Dependency>
            <Dependency>librsvg-devel</Dependency>
            <Dependency>libxml2-devel</Dependency>
            <Dependency>libxslt-devel</Dependency>
            <Dependency>libspectre-devel</Dependency>
        </RuntimeDependencies>
        <Files>
            <Path fileType="header">/usr/include</Path>
            <Path fileType="library">/usr/lib/pkgconfig</Path>
        </Files>
    </Package>
    
    <Package>
        <Name>goffice-docs</Name>
        <Summary>Development files for goffice</Summary>
        <RuntimeDependencies>
            <Dependency release="current">goffice</Dependency>
        </RuntimeDependencies>
        <Files>
            <Path fileType="data">/usr/share/gtk-doc</Path>
        </Files>
    </Package>
    
    <History>
        <Update release="4">
            <Date>2022-01-21</Date>
            <Version>0.10.51</Version>
            <Comment>Version bump.</Comment>
            <Name>Mustafa Cinasal</Name>
            <Email>muscnsl@gmail.com</Email>
        </Update>
        <Update release="3">
            <Date>2021-06-23</Date>
            <Version>0.10.50</Version>
            <Comment>Version bump.</Comment>
            <Name>Mustafa Cinasal</Name>
            <Email>muscnsl@gmail.com</Email>
        </Update>
        <Update release="2">
            <Date>2021-05-27</Date>
            <Version>0.10.49</Version>
            <Comment>Version bump.</Comment>
            <Name>Mustafa Cinasal</Name>
            <Email>muscnsl@gmail.com</Email>
        </Update>
        <Update release="1">
            <Date>2018-12-01</Date>
            <Version>0.10.44</Version>
            <Comment>First release</Comment>
            <Name>PisiLinux Community</Name>
            <Email>admins@pisilinux.org</Email>
        </Update>
    </History>
</PISI>
