
<?xml version="1.0" ?>
<!DOCTYPE PISI SYSTEM "http://www.pisilinux.org/projeler/pisi/pisi-spec.dtd">
<PISI>
    <Source>
        <Name>openssh</Name>
        <Homepage>http://www.openssh.com/</Homepage>
        <Packager>
            <Name>PisiLinux Community</Name>
            <Email>admins@pisilinux.org</Email>
        </Packager>
        <License>BSD</License>
        <IsA>app:console</IsA>
        <IsA>service</IsA>
        <Summary>Port of OpenBSD's free SSH release</Summary>
        <Description>OpenSSH is a FREE version of the SSH connectivity tools that technical users of the Internet rely on. Users of telnet, rlogin, and ftp may not realize that their password is transmitted across the Internet unencrypted, but it is. OpenSSH encrypts all traffic (including passwords) to effectively eliminate eavesdropping, connection hijacking, and other attacks.</Description>
        <Archive sha1sum="70e35d7d6386fe08abbd823b3a12a3ca44ac6d38" type="targz">http://ftp.icm.edu.pl/pub/OpenBSD/OpenSSH/portable/openssh-7.2p2.tar.gz</Archive>
        <BuildDependencies>
            <Dependency>libedit-devel</Dependency>
            <Dependency>zlib-devel</Dependency>
            <Dependency>openssl-devel</Dependency>
            <Dependency>mit-kerberos</Dependency>
            <!--Dependency>skey-devel</Dependency-->
            <Dependency>pam-devel</Dependency>
            <Dependency>e2fsprogs-devel</Dependency>
        </BuildDependencies>
        <Patches>
<!--             <Patch>curve25519pad.patch</Patch> -->
      </Patches>
    </Source>

    <Package>
        <Name>openssh</Name>
        <RuntimeDependencies>
            <Dependency>libedit</Dependency>
            <Dependency>zlib</Dependency>
            <Dependency>openssl</Dependency>
            <Dependency>mit-kerberos</Dependency>
            <!--Dependency>skey</Dependency-->
            <Dependency>pam</Dependency>
        </RuntimeDependencies>
        <Files>
            <Path fileType="config">/etc</Path>
            <Path fileType="executable">/usr/bin</Path>
            <Path fileType="executable">/usr/sbin</Path>
            <Path fileType="executable">/usr/libexec</Path>
            <Path fileType="library">/usr/lib</Path>
            <Path fileType="data">/usr/share/openssh</Path>
            <Path fileType="data">/var/empty</Path>
            <Path fileType="man">/usr/share/man</Path>
            <Path fileType="doc">/usr/share/doc</Path>
        </Files>
        <AdditionalFiles>
           <AdditionalFile owner="root" permission="0644" target="/etc/pam.d/sshd">sshd.pam</AdditionalFile>
        </AdditionalFiles>
        <Provides>
            <COMAR script="service.py">System.Service</COMAR>
        </Provides>
    </Package>

    <History>
        <Update release="1">
            <Date>2016-03-30</Date>
            <Version>7.2_p2</Version>
            <Comment>First release</Comment>
            <Name>Ertuğrul Erata</Name>
            <Email>ertugrulerata@gmail.com</Email>
        </Update>
    </History>
</PISI>
