
<?xml version="1.0" ?>
<!DOCTYPE PISI SYSTEM "http://www.pisilinux.org/projeler/pisi/pisi-spec.dtd">
<PISI>
    <Source>
        <Name>ModemManager</Name>
        <Homepage>http://projects.gnome.org/NetworkManager</Homepage>
        <Packager>
            <Name>PisiLinux Community</Name>
            <Email>admins@pisilinux.org</Email>
        </Packager>
        <License>LGPLv2.1</License>
        <IsA>app:console</IsA>
        <IsA>service</IsA>
        <Summary>A manager framework for mobile broadband modems</Summary>
        <Description>ModemManager provides a unified high level API for communicating with mobile broadband modems.</Description>
        <Archive sha1sum="e42e545516706746d647ce76c83ed1065cf2dafd" type="tarxz">http://www.freedesktop.org/software/ModemManager/ModemManager-1.4.12.tar.xz</Archive>
        <BuildDependencies>
            <Dependency>glib2-devel</Dependency>
            <Dependency>libgudev-devel</Dependency>
            <Dependency>libxslt-devel</Dependency>
            <Dependency>gobject-introspection-devel</Dependency>
            <Dependency>polkit-devel</Dependency>
            <Dependency>ppp-devel</Dependency>
            <Dependency>libqmi-devel</Dependency>
            <Dependency>libmbim-devel</Dependency>
            <Dependency>intltool</Dependency>
            <Dependency>gtk-doc</Dependency>
            <Dependency>docbook-xsl</Dependency>
            <Dependency>vala-devel</Dependency>
        </BuildDependencies>
    </Source>

    <Package>
        <Name>ModemManager</Name>
        <RuntimeDependencies>
            <Dependency>glib2</Dependency>
            <Dependency>libqmi</Dependency>
            <Dependency>polkit</Dependency>
            <Dependency>libmbim</Dependency>
            <Dependency>libgudev</Dependency>
            <Dependency>libmm-glib</Dependency> 
        </RuntimeDependencies>
        <Files>
            <Path fileType="doc">/usr/share/doc</Path>
            <Path fileType="executable">/usr/sbin</Path>
            <Path fileType="data">/usr/share/icons</Path>
            <Path fileType="localedata">/usr/share/locale</Path>
            <Path fileType="data">/usr/share/dbus-1</Path>
            <Path fileType="data">/usr/share/gir-1.0/ModemManager-1.0.gir</Path>
            <Path fileType="data">/lib/udev/rules.d/</Path>
            <Path fileType="data">/etc/dbus-1/system.d/</Path>
            <Path fileType="library">/usr/lib/ModemManager</Path>
            <Path fileType="library">/usr/lib/girepository-1.0/ModemManager-1.0.typelib</Path>
            <Path fileType="man">/usr/share/man/man8/ModemManager.8</Path>
            <Path fileType="data">/usr/share/gtk-doc</Path>
            <Path fileType="data">/usr/share/polkit-1</Path>
        </Files>
    </Package>

    <Package>
        <Name>ModemManager-devel</Name>
        <Summary>Development files for ModemManager</Summary>
        <RuntimeDependencies>
            <Dependency release="current">ModemManager</Dependency>
        </RuntimeDependencies>
        <Files>
            <Path fileType="header">/usr/include/ModemManager/</Path>
            <Path fileType="data">/usr/lib/pkgconfig/ModemManager.pc</Path>
        </Files>
    </Package>

    <Package>
        <Name>libmm-glib</Name>
        <Summary>D-Bus service for managing modems - shared libraries</Summary>
        <RuntimeDependencies>
            <Dependency>glib2</Dependency>
        </RuntimeDependencies>
        <Files>
            <Path fileType="executable">/usr/bin</Path>
            <Path fileType="data">/usr/share/vala/vapi/libmm-glib.vapi </Path>
            <Path fileType="data">/usr/share/vala/vapi/libmm-glib.deps </Path>
            <Path fileType="data">/usr/lib/libmm-glib.so*</Path>
            <Path fileType="man">/usr/share/man/man8/mmcli.8</Path>
        </Files>
    </Package>

    <Package>
        <Name>libmm-glib-devel</Name>
        <Summary>Development files for libmm-glib</Summary>
        <RuntimeDependencies>
            <Dependency release="current">libmm-glib</Dependency>
            <Dependency>glib2-devel</Dependency>
            <Dependency>ModemManager-devel</Dependency>
        </RuntimeDependencies>
        <Files>
            <Path fileType="header">/usr/include/libmm-glib/</Path>
            <Path fileType="data">/usr/lib/pkgconfig/mm-glib.pc</Path>
        </Files>
    </Package>

    <History>
        <Update release="1">
            <Date>2016-01-25</Date>
            <Version>1.4.12</Version>
            <Comment>First release</Comment>
            <Name>Ayhan Yalçınsoy</Name>
            <Email>ayhanyalcinsoy@pisilinux.org</Email>
        </Update>
    </History>
</PISI>
