<?xml version="1.0" ?>
<!DOCTYPE PISI SYSTEM "https://www.pisilinux.org/projeler/pisi/pisi-spec.dtd">
<PISI>
    <Source>
        <Name>marble</Name>
        <Homepage>http://edu.kde.org/applications/all/marble</Homepage>
        <Packager>
            <Name>PisiLinux Community</Name>
            <Email>admins@pisilinux.org</Email>
        </Packager>
        <License>GPLv2</License>
        <Icon>marble</Icon>
        <IsA>app:gui</IsA>
        <Summary>Virtual globe and eorld atlas</Summary>
        <Description>marble is a virtual globe and world atlas that you can use to learn more about the Earth.</Description>
        <Archive sha1sum="c5712595179b872e26fac59815ff80fbb4604f8c" type="tarxz">mirrors://kde/stable/release-service/24.12.2/src/marble-24.12.2.tar.xz</Archive>
        <BuildDependencies>
            <Dependency versionFrom="6.6.3">qt6-base-devel</Dependency>
            <Dependency versionFrom="6.6.3">qt6-designer-devel</Dependency>
            <Dependency versionFrom="6.6.3">qt6-svg-devel</Dependency>
            <Dependency versionFrom="6.6.3">qt6-declarative-devel</Dependency>
            <Dependency versionFrom="6.6.3">qt6-sql-postgresql</Dependency>
            <Dependency versionFrom="6.6.3">qt6-sql-mysql</Dependency>
            <Dependency versionFrom="6.6.3">qt6-sql-odbc</Dependency>
            <Dependency versionFrom="6.6.3">qt6-sql-sqlite</Dependency>
            <Dependency versionFrom="6.6.3">qt6-linguist</Dependency>
            <Dependency versionFrom="6.6.3">qt6-webengine-devel</Dependency>
            <Dependency versionFrom="6.6.3">qt6-5compat-devel</Dependency>
            <Dependency>kdoctools-devel</Dependency>
            <Dependency>qt6-phonon-devel</Dependency>
            <Dependency>kio-devel</Dependency>
            <Dependency>quazip-devel</Dependency>
            <Dependency>kwallet-devel</Dependency>
            <Dependency>knewstuff-devel</Dependency>
            <Dependency>kparts-devel</Dependency>
            <Dependency>kcoreaddons-devel</Dependency>
            <Dependency>ki18n-devel</Dependency>
            <Dependency>kconfig-devel</Dependency>
            <Dependency>krunner-devel</Dependency>
            <Dependency>kservice-devel</Dependency>
            <Dependency>libwlocate-devel</Dependency>
            <Dependency>shared-mime-info</Dependency>
            <Dependency>qt6-serialport-devel</Dependency>
            <Dependency>plasma-desktop</Dependency>
            <Dependency>extra-cmake-modules</Dependency>
        </BuildDependencies>
    </Source>

    <Package>
        <Name>marble</Name>
        <RuntimeDependencies>
            <Dependency>kio</Dependency>
            <Dependency>zlib</Dependency>
            <Dependency>ki18n</Dependency>
            <Dependency>kcrash</Dependency>
            <Dependency>kparts</Dependency>
            <Dependency>libgcc</Dependency>
            <Dependency>kconfig</Dependency>
            <Dependency>krunner</Dependency>
            <Dependency>kxmlgui</Dependency>
            <Dependency versionFrom="6.6.3">qt6-svg</Dependency>
            <Dependency versionFrom="6.6.3">qt6-base</Dependency>
            <Dependency>knewstuff</Dependency>
            <Dependency>libwlocate</Dependency>
            <Dependency>qt6-phonon</Dependency>
            <Dependency>kcoreaddons</Dependency>
            <Dependency>kconfigwidgets</Dependency>
            <Dependency>kwidgetsaddons</Dependency>
            <Dependency versionFrom="6.6.3">qt6-declarative</Dependency>
            <Dependency versionFrom="6.6.3">qt6-serialport</Dependency>
        </RuntimeDependencies>
        <Files>
            <Path fileType="library">/usr/lib</Path>
            <Path fileType="executable">/usr/bin</Path>
            <Path fileType="data">/usr/share</Path>
            <Path fileType="data">/usr/share/appdata</Path>
            <Path fileType="data">/usr/share/applications</Path>
            <Path fileType="data">/usr/share/config.kcfg</Path>
            <Path fileType="doc">/usr/share/doc</Path>
            <Path fileType="data">/usr/share/icons</Path>
            <Path fileType="data">/usr/share/kservices5</Path>
            <Path fileType="data">/usr/share/kxmlgui5</Path>
            <Path fileType="data">/usr/share/marble</Path>
            <Path fileType="config">/etc/xdg</Path>
        </Files>
        <Replaces>
            <Package>marble-kf6</Package>
        </Replaces>
    </Package>

    <Package>
        <Name>marble-devel</Name>
        <Summary>Development files for marble</Summary>
        <RuntimeDependencies>
            <Dependency release="current">marble</Dependency>
        </RuntimeDependencies>
        <Files>
            <Path fileType="header">/usr/include</Path>
        </Files>
        <Replaces>
            <Package>marble-kf6-devel</Package>
        </Replaces>
    </Package>

    <History>
        <Update release="58">
            <Date>2025-02-06</Date>
            <Version>24.12.2</Version>
            <Comment>Version bump.</Comment>
            <Name>Pisi Linux Community</Name>
            <Email>admin@pisilinux.org</Email>
        </Update>
        <Update release="57">
            <Date>2025-01-09</Date>
            <Version>24.12.1</Version>
            <Comment>First release</Comment>
            <Name>Pisi Linux Community</Name>
            <Email>admin@pisilinux.org</Email>
        </Update>
    </History>
</PISI>
