<?xml version="1.0" ?>
<!DOCTYPE PISI SYSTEM "http://www.pisilinux.org/projeler/pisi/pisi-spec.dtd">
<PISI>
    <Source>
        <Name>mate-backgrounds</Name>
        <Homepage>http://www.mate-desktop.org</Homepage>
        <Packager>
            <Name>Ayhan Yalçınsoy</Name>
            <Email>ayhanyalcinsoy@pisilinux.org</Email>
        </Packager>
        <License>GPLv2+</License>
        <IsA>data</IsA>
        <Summary>Default wallpapers for the Mate desktop</Summary>
        <Description>gnome-backgrounds contains default wallpapers for the Mate desktop.</Description>
	<Archive sha1sum="a8588634fb9a9d0c76871b58fb57101eeadab41a" type="tarxz">http://pub.mate-desktop.org/releases/1.27/mate-backgrounds-1.27.1.tar.xz</Archive>
	    <BuildDependencies>
             <Dependency>intltool</Dependency>
             <Dependency versionFrom="1.27.0">mate-common</Dependency>
        </BuildDependencies>
        <Patches>
            <Patch>mate-backgrounds-add-image.patch</Patch>
        </Patches>
        <AdditionalFiles>
            <AdditionalFile target="nature/1.jpg">nature/1.jpg</AdditionalFile>
            <AdditionalFile target="nature/2.jpg">nature/2.jpg</AdditionalFile>
            <AdditionalFile target="nature/3.jpg">nature/3.jpg</AdditionalFile>
            <AdditionalFile target="nature/4.jpg">nature/4.jpg</AdditionalFile>
            <AdditionalFile target="nature/5.jpg">nature/5.jpg</AdditionalFile>
            <AdditionalFile target="nature/6.jpg">nature/6.jpg</AdditionalFile>
            <AdditionalFile target="nature/7.jpg">nature/7.jpg</AdditionalFile>
            <AdditionalFile target="nature/8.jpg">nature/8.jpg</AdditionalFile>
        </AdditionalFiles>
    </Source>

    <Package>
        <Name>mate-backgrounds</Name>
        <Files>
            <Path fileType="doc">/usr/share/doc</Path>
            <Path fileType="data">/usr/share/pixmaps</Path>
            <Path fileType="localedata">/usr/share/locale</Path>
            <Path fileType="data">/usr/share/backgrounds</Path>
            <Path fileType="doc">/usr/share/mate-background-properties</Path>
        </Files>
    </Package>

    <History>
        <Update release="6">
            <Date>2023-04-17</Date>
            <Version>1.27.1</Version>
            <Comment>Version bump.</Comment>
            <Name>Mustafa Cinasal</Name>
            <Email>muscnsl@gmail.com</Email>
        </Update>
        <Update release="5">
            <Date>2021-09-07</Date>
            <Version>1.26.0</Version>
            <Comment>Version bump.</Comment>
            <Name>Mustafa Cinasal</Name>
            <Email>muscnsl@gmail.com</Email>
        </Update>
        <Update release="4">
            <Date>2020-08-23</Date>
            <Version>1.25.0</Version>
            <Comment>Version bump.</Comment>
            <Name>Mustafa Cinasal</Name>
            <Email>muscnsl@gmail.com</Email>
        </Update>
        <Update release="3">
            <Date>2020-06-29</Date>
            <Version>1.24.1</Version>
            <Comment>Version bump.</Comment>
            <Name>Mustafa Cinasal</Name>
            <Email>muscnsl@gmail.com</Email>
        </Update>
        <Update release="2">
            <Date>2020-04-03</Date>
            <Version>1.24.1</Version>
            <Comment>Version bump.</Comment>
            <Name>Mustafa Cinasal</Name>
            <Email>muscnsl@gmail.com</Email>
        </Update>
        <Update release="1">
            <Date>2020-02-13</Date>
            <Version>1.22.0</Version>
            <Comment>First release</Comment>
            <Name>Ayhan Yalçınsoy</Name>
            <Email>ayhanyalcinsoy@pisilinux.org</Email>
        </Update>
    </History>
</PISI>
