<?xml version="1.0" ?>
<!DOCTYPE PISI SYSTEM "https://www.pisilinux.org/projeler/pisi/pisi-spec.dtd">
<PISI>
    <Source>
        <Name>kompare</Name>
        <Homepage>http://www.kde.org/</Homepage>
        <Packager>
            <Name>Pisi Linux Admins</Name>
            <Email>admins@pisilinux.org</Email>
        </Packager>
        <License>GPLv2</License>
        <IsA>app:gui</IsA>
        <PartOf>desktop.kde.sdk</PartOf>
        <Summary>File difference viewer</Summary>
        <Description>Diff/Patch Frontend. </Description>
        <Archive sha1sum="893fca7e2db0656a1cfef58d3498bf77c08be6fe" type="tarxz">mirrors://kde/stable/release-service/24.12.2/src/kompare-24.12.2.tar.xz</Archive>
        <BuildDependencies>
            <Dependency>extra-cmake-modules</Dependency>
            <Dependency>kdoctools-devel</Dependency>
            <Dependency versionFrom="6.6.3">qt6-base-devel</Dependency>
            <Dependency>gettext-devel</Dependency>
            <Dependency versionFrom="24.12.2">libkomparediff2-devel</Dependency>
            <Dependency>kcoreaddons-devel</Dependency>
            <Dependency>kcodecs-devel</Dependency>
            <Dependency>kiconthemes-devel</Dependency>
            <Dependency>kjobwidgets-devel</Dependency>
            <Dependency>kconfig-devel</Dependency>
            <Dependency>kparts-devel</Dependency>
            <Dependency>ktexteditor-devel</Dependency>
            <Dependency>kwidgetsaddons-devel</Dependency>
        </BuildDependencies>
    </Source>

    <Package>
        <Name>kompare</Name>
        <RuntimeDependencies>
            <Dependency versionFrom="6.6.3">qt6-base</Dependency>
            <Dependency>libkomparediff2</Dependency>
            <Dependency>kio</Dependency>
            <Dependency>ki18n</Dependency>
            <Dependency>kparts</Dependency>
            <Dependency>libgcc</Dependency>
            <Dependency>kcodecs</Dependency>
            <Dependency>kconfig</Dependency>
            <Dependency>kxmlgui</Dependency>
            <Dependency>kservice</Dependency>
            <Dependency>kcompletion</Dependency>
            <Dependency>kcoreaddons</Dependency>
            <Dependency>kiconthemes</Dependency>
            <Dependency>kjobwidgets</Dependency>
            <Dependency>ktexteditor</Dependency>
            <Dependency>kconfigwidgets</Dependency>
            <Dependency>kwidgetsaddons</Dependency>
        </RuntimeDependencies>
        <Replaces>
            <Package>kdesdk</Package>
            <Package>kompare-kf6</Package>
        </Replaces>
        <Conflicts>
            <Package>kdesdk</Package>
        </Conflicts>
        <Files>
            <Path fileType="data">/usr/share</Path>
            <Path fileType="library">/usr/lib</Path>
            <Path fileType="library">/usr/lib/qt6</Path>
            <Path fileType="doc">/usr/share/doc</Path>
            <Path fileType="executable">/usr/bin</Path>
            <Path fileType="header">/usr/include</Path>
        </Files>
    </Package>

    <History>
        <Update release="58">
            <Date>2025-02-06</Date>
            <Version>24.12.2</Version>
            <Comment>Version bump.</Comment>
            <Name>Pisi Linux Community</Name>
            <Email>admin@pisilinux.org</Email>
        </Update>
        <Update release="57">
            <Date>2025-01-09</Date>
            <Version>24.12.1</Version>
            <Comment>First release</Comment>
            <Name>Pisi Linux Community</Name>
            <Email>admin@pisilinux.org</Email>
        </Update>
    </History>
</PISI>
